{
    "app":{
        "exotic_armor":{
            "stat_window": "content",
            "perk_name": "_3sBrL",
            "description": "dd6Tm",
            "new_div_loc": "_2WYTx",
            "new_div_css": "_35diU"
        }
    },
    "beta":{
        "exotic_armor":{
            "stat_window": "",
            "perk_name": "ArchetypeSocket-m_name-3sBrL",
            "description": "ItemSocketsGeneral-m_exoticDescription-dd6Tm",
            "loc_for_new_div": "ArchetypeSocket-m_row-2WYTx",
            "armor_perk_name": "ArchetypeSocket-m_info-35diU"
        },
        "extra_weapon_stats":{
            "stat_window": "content",
            "wep_link": ".ItemPopupHeader-m_title-2hFLg > a",
            "wep_stats": "ItemStats-m_stats-3ywbI",
            "wep_stat_name_class": "ItemStat-m_statName-1XPu7",
            "wep_stat_value_class": "ItemStat-m_value-3utrN"
        },
        "weapon_perks": {
            
        },
        "d2_gunsmith": {
            "stat_window": "content",
            "location": ".ActionButton-m_actionButton-V9iV5",
            "class": "ActionButton-m_actionButton-V9iV5",
            "button_text_hide": "DesktopItemActions-m_collapsed-doC6W",
            "click_event": "DesktopItemActions-m_collapseButton-2xfla",
            "link": ".ItemPopupHeader-m_title-2hFLg > a"
        },
        "sources_and_more_menu": {
            "header_button": "Header-m_headerLinks-2hYs2",
            "button_class": "Header-m_menuItem-3G0SM",
            "dark_mode_line_1": ".app::before",
            "dark_mode_line_2": ".Header-m_header-1eaLe, .store-header, .HeaderShadowDiv-m_cover-1R3rf",
            "dark_mode_line_3": ".BadgeInfo-m_badge-hcIF4",
            "dark_mode_line_4": ".item-img",
            "dark_mode_line_5": ".ItemIcon-m_borderless-1AaJE",
            "dark_mode_line_6": ".rating-icon.godroll",
            "dark_mode_line_7": ".ItemTable-m_table-ANdPB>div"
        }
    }
}